odoo9_addon_product_variant_configurator-9.0.1.0.1-py2.7-nspkg.pth
odoo9_addon_product_variant_configurator-9.0.1.0.1.dist-info/METADATA
odoo9_addon_product_variant_configurator-9.0.1.0.1.dist-info/RECORD
odoo9_addon_product_variant_configurator-9.0.1.0.1.dist-info/WHEEL
odoo9_addon_product_variant_configurator-9.0.1.0.1.dist-info/namespace_packages.txt
odoo9_addon_product_variant_configurator-9.0.1.0.1.dist-info/top_level.txt
odoo_addons/product_variant_configurator/README.rst
odoo_addons/product_variant_configurator/__init__.py
odoo_addons/product_variant_configurator/__openerp__.py
odoo_addons/product_variant_configurator/i18n/es.po
odoo_addons/product_variant_configurator/i18n/fr.po
odoo_addons/product_variant_configurator/i18n/it.po
odoo_addons/product_variant_configurator/i18n/product_variant_configurator.pot
odoo_addons/product_variant_configurator/i18n/pt_BR.po
odoo_addons/product_variant_configurator/i18n/ro.po
odoo_addons/product_variant_configurator/i18n/sl.po
odoo_addons/product_variant_configurator/migrations/8.0.2.0.0/pre-migration.py
odoo_addons/product_variant_configurator/models/__init__.py
odoo_addons/product_variant_configurator/models/pricelist.py
odoo_addons/product_variant_configurator/models/product_attribute_line.py
odoo_addons/product_variant_configurator/models/product_attribute_price.py
odoo_addons/product_variant_configurator/models/product_attribute_value.py
odoo_addons/product_variant_configurator/models/product_category.py
odoo_addons/product_variant_configurator/models/product_configurator.py
odoo_addons/product_variant_configurator/models/product_configurator_attribute.py
odoo_addons/product_variant_configurator/models/product_product.py
odoo_addons/product_variant_configurator/models/product_template.py
odoo_addons/product_variant_configurator/security/product_configurator_attribute.xml
odoo_addons/product_variant_configurator/security/product_configurator_security.xml
odoo_addons/product_variant_configurator/static/description/icon.png
odoo_addons/product_variant_configurator/tests/__init__.py
odoo_addons/product_variant_configurator/tests/test_product_configurator_attribute.py
odoo_addons/product_variant_configurator/tests/test_product_pricelist.py
odoo_addons/product_variant_configurator/tests/test_product_variant_configurator.py
